speech_dataset_generator/__init__.py
speech_dataset_generator/main.py
speech_dataset_generator/audio_manager/__init__.py
speech_dataset_generator/audio_manager/audio_manager.py
speech_dataset_generator/audio_processor/__init__.py
speech_dataset_generator/audio_processor/audio_processor.py
speech_dataset_generator/dataset_generator/__init__.py
speech_dataset_generator/dataset_generator/dataset_generator.py
speech_dataset_generator/speech_rate/__init__.py
speech_dataset_generator/speech_rate/speech_rate.py
speech_dataset_generator/utils/__init__.py
speech_dataset_generator/utils/utils.py
speech_dataset_generator-1.0.0.dist-info/LICENSE
speech_dataset_generator-1.0.0.dist-info/METADATA
speech_dataset_generator-1.0.0.dist-info/WHEEL
speech_dataset_generator-1.0.0.dist-info/dependency_links.txt
speech_dataset_generator-1.0.0.dist-info/entry_points.txt
speech_dataset_generator-1.0.0.dist-info/top_level.txt
speech_dataset_generator-1.0.0.dist-info/RECORD
