Metadata-Version: 2.1
Name: speech-dataset-generator
Version: 1.0.0
Summary: 🔊 Create labeled datasets, enhance audio quality, identify speakers, support diverse dataset types. 🎧👥📊 Advanced audio processing.
Home-page: https://github.com/davidmartinrius/speech-dataset-generator
Author: David Martin Rius
Author-email: 0991592@gmail.com
License: UNKNOWN
Project-URL: Source, https://github.com/davidmartinrius/speech-dataset-generator
Project-URL: Issues, https://github.com/davidmartinrius/speech-dataset-generator/issues
Platform: UNKNOWN
Requires-Python: >=3.10
License-File: LICENSE
Requires-Dist: chromadb ==0.4.23
Requires-Dist: deepfilternet
Requires-Dist: faster-whisper ==0.10.1
Requires-Dist: inaSpeechSegmenter ==0.7.7
Requires-Dist: konlpy ==0.6.0
Requires-Dist: pydub ==0.25.1
Requires-Dist: pyphen ==0.14.0
Requires-Dist: pypinyin ==0.50.0
Requires-Dist: python-dotenv ==1.0.1
Requires-Dist: speechbrain ==0.5.16
Requires-Dist: whisperx ==3.1.1
Requires-Dist: yt-dlp
